dbtdiff/__main__.py
dbtdiff-0.2.2.dist-info/licenses/LICENSE
dbtdiff-0.2.2.dist-info/METADATA
dbtdiff-0.2.2.dist-info/WHEEL
dbtdiff-0.2.2.dist-info/entry_points.txt
dbtdiff-0.2.2.dist-info/top_level.txt
dbtdiff-0.2.2.dist-info/RECORD
