Metadata-Version: 2.4
Name: dbtdiff
Version: 0.2.2
Summary: Run dbt on changed models with model+ chaining.
Author: Garrett McClintock
License: MIT
Requires-Python: >=3.7
License-File: LICENSE
Dynamic: license-file
